setup.py
bin/spotifylyrics
spotifylyrics/__init__.py
spotifylyrics.egg-info/PKG-INFO
spotifylyrics.egg-info/SOURCES.txt
spotifylyrics.egg-info/dependency_links.txt
spotifylyrics.egg-info/not-zip-safe
spotifylyrics.egg-info/top_level.txt