Metadata-Version: 1.0
Name: spotifylyrics
Version: 1.0
Summary: Displays lyrics for spotify songs
Home-page: http://github.com
Author: Yask Srivastava
Author-email: yask123@gmail.com
License: MIT
Platform: UNKNOWN
